CHANGELOG.md
LICENSE
MANIFEST.in
README.md
setup.py
plugins/__init__.py
plugins/repeat.py
rtmbot/__init__.py
rtmbot/core.py
rtmbot.egg-info/PKG-INFO
rtmbot.egg-info/SOURCES.txt
rtmbot.egg-info/dependency_links.txt
rtmbot.egg-info/entry_points.txt
rtmbot.egg-info/requires.txt
rtmbot.egg-info/top_level.txt
rtmbot/bin/__init__.py
rtmbot/bin/run_rtmbot.py
rtmbot/utils/__init__.py
rtmbot/utils/module_loading.py