Metadata-Version: 1.0
Name: rtmbot
Version: 0.4.1
Summary: A Slack bot written in python that connects via the RTM API.
Home-page: https://github.com/slackhq/python-rtmbot
Author: Ryan Huber and Jeff Ammons
Author-email: developers@slack.com
License: UNKNOWN
Platform: UNKNOWN
